ACM/__main__.py
ACM/anatomy.py
ACM/calibration.py
ACM/em.py
ACM/em_helper.py
ACM/em_run.py
ACM/export.py
ACM/fitting.py
ACM/helper.py
ACM/initialization.py
ACM/interp_3d.py
ACM/kalman.py
ACM/model.py
ACM/optimization.py
ACM/routines_math.py
ACM/tools.py
ACM/gui/__init__.py
ACM/gui/viewer.py
bbo_acm-0.2.4.dist-info/LICENSE
bbo_acm-0.2.4.dist-info/METADATA
bbo_acm-0.2.4.dist-info/WHEEL
bbo_acm-0.2.4.dist-info/top_level.txt
bbo_acm-0.2.4.dist-info/RECORD
