Metadata-Version: 2.1
Name: bbo-acm
Version: 0.2.4
Summary: Anatomically constraint pose reconstruction from video data
Home-page: https://github.com/bbo-lab/ACM
Author: Arne Monsees, BBO lab
Author-email: bbo-admin@caesar.de
License: LGPLv2+
Platform: UNKNOWN
Classifier: License :: OSI Approved :: GNU Lesser General Public License v2 or later (LGPLv2+)
Classifier: Programming Language :: Python :: 3
Classifier: Programming Language :: Python :: 3.6
Classifier: Programming Language :: Python :: 3.7
Classifier: Programming Language :: Python :: 3.8
License-File: LICENSE
Requires-Dist: numpy
Requires-Dist: torch
Requires-Dist: scipy
Requires-Dist: argparse
